{"right_sidebar":{"search-3":{"title":"Search"},"categories-3":{"title":"Categories","count":0,"hierarchical":0,"dropdown":0},"populat_post_widget-1":{"title":"Popular posts","post_per_widget":""},"archives-3":{"title":"Archives","count":0,"dropdown":0}},"left_sidebar":{"search-4":{"title":"Search"},"categories-4":{"title":"Categories","count":0,"hierarchical":0,"dropdown":0},"populat_post_widget-2":{"title":"Popular posts","post_per_widget":""},"archives-4":{"title":"Archives","count":0,"dropdown":0}},"property_list_sidebar":{"property_filter_widget-2":{"title":"Find Your Dream Home"},"featured_property_widget-2":{"title":"Featured Property"}}}